{
	"Sheet1": [{
		"序号": 1,
		"模型编号": "Object1163",
		"经度": 116.06611344,
		"纬度": 30.22700452,
		"海拔高度/m": 21.81319,
		"树高度/m": 7.12664
	}, {
		"序号": 2,
		"模型编号": "Object1164",
		"经度": 116.06521234,
		"纬度": 30.2265598,
		"海拔高度/m": 24.21319,
		"树高度/m": 5.260744
	}, {
		"序号": 3,
		"模型编号": "Object1165",
		"经度": 116.0648099,
		"纬度": 30.22553582,
		"海拔高度/m": 24.21319,
		"树高度/m": 5.249006
	}, {
		"序号": 4,
		"模型编号": "Object862",
		"经度": 116.06848307,
		"纬度": 30.22882401,
		"海拔高度/m": 31.618481,
		"树高度/m": 10.35478
	}, {
		"序号": 5,
		"模型编号": "Object876",
		"经度": 116.06358302,
		"纬度": 30.22507238,
		"海拔高度/m": 32.309498,
		"树高度/m": 10.360538
	}, {
		"序号": 6,
		"模型编号": "Object1161",
		"经度": 116.06748477,
		"纬度": 30.22918513,
		"海拔高度/m": 32.61319,
		"树高度/m": 14.5102
	}, {
		"序号": 7,
		"模型编号": "Object1162",
		"经度": 116.06717455,
		"纬度": 30.22869997,
		"海拔高度/m": 32.61319,
		"树高度/m": 15.317212
	}, {
		"序号": 8,
		"模型编号": "Object865",
		"经度": 116.06783208,
		"纬度": 30.23037623,
		"海拔高度/m": 33.312481,
		"树高度/m": 13.027104
	}, {
		"序号": 9,
		"模型编号": "Object839",
		"经度": 116.08446395,
		"纬度": 30.24430146,
		"海拔高度/m": 34.713055,
		"树高度/m": 6.50292
	}, {
		"序号": 10,
		"模型编号": "Object883",
		"经度": 116.0641986,
		"纬度": 30.22489822,
		"海拔高度/m": 34.908043,
		"树高度/m": 5.105242
	}, {
		"序号": 11,
		"模型编号": "Object843",
		"经度": 116.07691279,
		"纬度": 30.24282634,
		"海拔高度/m": 35.01305,
		"树高度/m": 7.062526
	}, {
		"序号": 12,
		"模型编号": "Object841",
		"经度": 116.07711299,
		"纬度": 30.24260122,
		"海拔高度/m": 35.613052,
		"树高度/m": 9.11144
	}, {
		"序号": 13,
		"模型编号": "Object848",
		"经度": 116.07415979,
		"纬度": 30.23749722,
		"海拔高度/m": 35.705616,
		"树高度/m": 9.654532
	}, {
		"序号": 14,
		"模型编号": "Object840",
		"经度": 116.08362282,
		"纬度": 30.24426995,
		"海拔高度/m": 36.813053,
		"树高度/m": 5.38942
	}, {
		"序号": 15,
		"模型编号": "Object829",
		"经度": 116.08318287,
		"纬度": 30.24551308,
		"海拔高度/m": 37.113056,
		"树高度/m": 4.141814
	}, {
		"序号": 16,
		"模型编号": "Object874",
		"经度": 116.0623797,
		"纬度": 30.22461105,
		"海拔高度/m": 37.4095,
		"树高度/m": 10.230976
	}, {
		"序号": 17,
		"模型编号": "Object868",
		"经度": 116.06728212,
		"纬度": 30.22820565,
		"海拔高度/m": 38.009502,
		"树高度/m": 17.451388
	}, {
		"序号": 18,
		"模型编号": "Object824",
		"经度": 116.08269543,
		"纬度": 30.24437843,
		"海拔高度/m": 38.013058,
		"树高度/m": 9.563606
	}, {
		"序号": 19,
		"模型编号": "Object851",
		"经度": 116.07340899,
		"纬度": 30.23712349,
		"海拔高度/m": 38.105614,
		"树高度/m": 5.244944
	}, {
		"序号": 20,
		"模型编号": "Object872",
		"经度": 116.06189319,
		"纬度": 30.22398524,
		"海拔高度/m": 38.309502,
		"树高度/m": 12.56802
	}, {
		"序号": 21,
		"模型编号": "Object845",
		"经度": 116.0767763,
		"纬度": 30.24154156,
		"海拔高度/m": 38.913052,
		"树高度/m": 8.203294
	}, {
		"序号": 22,
		"模型编号": "Object825",
		"经度": 116.08284183,
		"纬度": 30.2443704,
		"海拔高度/m": 39.813057,
		"树高度/m": 11.77635
	}, {
		"序号": 23,
		"模型编号": "Object873",
		"经度": 116.06237104,
		"纬度": 30.2248688,
		"海拔高度/m": 40.4095,
		"树高度/m": 14.23689
	}, {
		"序号": 24,
		"模型编号": "Object842",
		"经度": 116.07741339,
		"纬度": 30.2427719,
		"海拔高度/m": 40.413052,
		"树高度/m": 4.082652
	}, {
		"序号": 25,
		"模型编号": "Object832",
		"经度": 116.08283017,
		"纬度": 30.24555967,
		"海拔高度/m": 40.413055,
		"树高度/m": 9.02044
	}, {
		"序号": 26,
		"模型编号": "Object836",
		"经度": 116.08532671,
		"纬度": 30.24435366,
		"海拔高度/m": 40.413055,
		"树高度/m": 7.387712
	}, {
		"序号": 27,
		"模型编号": "Object884",
		"经度": 116.0651382,
		"纬度": 30.22487881,
		"海拔高度/m": 40.855759,
		"树高度/m": 7.393084
	}, {
		"序号": 28,
		"模型编号": "Object869",
		"经度": 116.06566049,
		"纬度": 30.22639396,
		"海拔高度/m": 41.009502,
		"树高度/m": 16.192974
	}, {
		"序号": 29,
		"模型编号": "Object863",
		"经度": 116.06801756,
		"纬度": 30.23010051,
		"海拔高度/m": 41.518482,
		"树高度/m": 13.265694
	}, {
		"序号": 30,
		"模型编号": "Object864",
		"经度": 116.06857251,
		"纬度": 30.22952875,
		"海拔高度/m": 41.518482,
		"树高度/m": 13.350012
	}, {
		"序号": 31,
		"模型编号": "Object826",
		"经度": 116.08305387,
		"纬度": 30.24435111,
		"海拔高度/m": 41.613056,
		"树高度/m": 10.246488
	}, {
		"序号": 32,
		"模型编号": "Object866",
		"经度": 116.06844076,
		"纬度": 30.23142865,
		"海拔高度/m": 41.85751,
		"树高度/m": 11.588506
	}, {
		"序号": 33,
		"模型编号": "Object844",
		"经度": 116.07896683,
		"纬度": 30.24389539,
		"海拔高度/m": 41.913052,
		"树高度/m": 7.836274
	}, {
		"序号": 34,
		"模型编号": "Object1144",
		"经度": 116.08287896,
		"纬度": 30.24538991,
		"海拔高度/m": 41.913177,
		"树高度/m": 9.197024
	}, {
		"序号": 35,
		"模型编号": "Object1108",
		"经度": 116.05323966,
		"纬度": 30.21293503,
		"海拔高度/m": 42.339352,
		"树高度/m": 3.418528
	}, {
		"序号": 36,
		"模型编号": "Object891",
		"经度": 116.05719294,
		"纬度": 30.21614908,
		"海拔高度/m": 42.691963,
		"树高度/m": 7.546838
	}, {
		"序号": 37,
		"模型编号": "Object815",
		"经度": 116.12156306,
		"纬度": 30.24803322,
		"海拔高度/m": 42.920387,
		"树高度/m": 10.37299
	}, {
		"序号": 38,
		"模型编号": "Object828",
		"经度": 116.0835747,
		"纬度": 30.24472351,
		"海拔高度/m": 43.113056,
		"树高度/m": 4.236244
	}, {
		"序号": 39,
		"模型编号": "Object846",
		"经度": 116.07435026,
		"纬度": 30.23860122,
		"海拔高度/m": 43.259323,
		"树高度/m": 11.389004
	}, {
		"序号": 40,
		"模型编号": "Object853",
		"经度": 116.07333659,
		"纬度": 30.23622035,
		"海拔高度/m": 43.505615,
		"树高度/m": 9.646522
	}, {
		"序号": 41,
		"模型编号": "Object870",
		"经度": 116.0637598,
		"纬度": 30.2247029,
		"海拔高度/m": 43.709503,
		"树高度/m": 8.214004
	}, {
		"序号": 42,
		"模型编号": "Object837",
		"经度": 116.0856236,
		"纬度": 30.24476048,
		"海拔高度/m": 44.013054,
		"树高度/m": 8.57074
	}, {
		"序号": 43,
		"模型编号": "Object838",
		"经度": 116.08478977,
		"纬度": 30.24498866,
		"海拔高度/m": 44.013054,
		"树高度/m": 3.893084
	}, {
		"序号": 44,
		"模型编号": "Object1109",
		"经度": 116.0529977,
		"纬度": 30.21318674,
		"海拔高度/m": 44.43935,
		"树高度/m": 3.841884
	}, {
		"序号": 45,
		"模型编号": "Object827",
		"经度": 116.08340786,
		"纬度": 30.24445693,
		"海拔高度/m": 44.913055,
		"树高度/m": 12.252946
	}, {
		"序号": 46,
		"模型编号": "Object1151",
		"经度": 116.07546265,
		"纬度": 30.24244276,
		"海拔高度/m": 45.513187,
		"树高度/m": 7.78404
	}, {
		"序号": 47,
		"模型编号": "Object867",
		"经度": 116.06956768,
		"纬度": 30.23116038,
		"海拔高度/m": 45.757507,
		"树高度/m": 4.651698
	}, {
		"序号": 48,
		"模型编号": "Object879",
		"经度": 116.10775673,
		"纬度": 30.24727369,
		"海拔高度/m": 45.769154,
		"树高度/m": 6.14309
	}, {
		"序号": 49,
		"模型编号": "Object871",
		"经度": 116.06236798,
		"纬度": 30.22438684,
		"海拔高度/m": 45.809502,
		"树高度/m": 10.8502
	}, {
		"序号": 50,
		"模型编号": "Object1105",
		"经度": 116.05408746,
		"纬度": 30.21253692,
		"海拔高度/m": 45.939354,
		"树高度/m": 3.984798
	}, {
		"序号": 51,
		"模型编号": "Object833",
		"经度": 116.0845519,
		"纬度": 30.24589301,
		"海拔高度/m": 46.413055,
		"树高度/m": 5.494626
	}, {
		"序号": 52,
		"模型编号": "Object1107",
		"经度": 116.05396933,
		"纬度": 30.21309648,
		"海拔高度/m": 46.539352,
		"树高度/m": 3.502192
	}, {
		"序号": 53,
		"模型编号": "Object1145",
		"经度": 116.07904007,
		"纬度": 30.2441864,
		"海拔高度/m": 47.01318,
		"树高度/m": 14.155114
	}, {
		"序号": 54,
		"模型编号": "Object847",
		"经度": 116.07481708,
		"纬度": 30.23863359,
		"海拔高度/m": 47.159325,
		"树高度/m": 8.837244
	}, {
		"序号": 55,
		"模型编号": "Object1179",
		"经度": 116.05533696,
		"纬度": 30.21586757,
		"海拔高度/m": 47.236866,
		"树高度/m": 5.720554
	}, {
		"序号": 56,
		"模型编号": "Object803",
		"经度": 116.12486876,
		"纬度": 30.24889132,
		"海拔高度/m": 47.420387,
		"树高度/m": 11.016736
	}, {
		"序号": 57,
		"模型编号": "Object1168",
		"经度": 116.06238371,
		"纬度": 30.22397264,
		"海拔高度/m": 47.613194,
		"树高度/m": 7.081346
	}, {
		"序号": 58,
		"模型编号": "Object854",
		"经度": 116.07311754,
		"纬度": 30.2361039,
		"海拔高度/m": 47.705616,
		"树高度/m": 7.91158
	}, {
		"序号": 59,
		"模型编号": "Object946",
		"经度": 116.10536516,
		"纬度": 30.29046238,
		"海拔高度/m": 47.861202,
		"树高度/m": 13.975844
	}, {
		"序号": 60,
		"模型编号": "Object804",
		"经度": 116.12532186,
		"纬度": 30.24917763,
		"海拔高度/m": 48.020386,
		"树高度/m": 9.01611
	}, {
		"序号": 61,
		"模型编号": "Object805",
		"经度": 116.12561052,
		"纬度": 30.24923597,
		"海拔高度/m": 48.020386,
		"树高度/m": 9.233244
	}, {
		"序号": 62,
		"模型编号": "Object875",
		"经度": 116.06320892,
		"纬度": 30.22468658,
		"海拔高度/m": 48.209499,
		"树高度/m": 9.245082
	}, {
		"序号": 63,
		"模型编号": "Object834",
		"经度": 116.08443441,
		"纬度": 30.24601863,
		"海拔高度/m": 48.213055,
		"树高度/m": 3.730634
	}, {
		"序号": 64,
		"模型编号": "Object1174",
		"经度": 116.05540796,
		"纬度": 30.21476222,
		"海拔高度/m": 48.928364,
		"树高度/m": 9.657612
	}, {
		"序号": 65,
		"模型编号": "Object1175",
		"经度": 116.05561852,
		"纬度": 30.21453535,
		"海拔高度/m": 48.928364,
		"树高度/m": 6.556608
	}, {
		"序号": 66,
		"模型编号": "Object1149",
		"经度": 116.07729867,
		"纬度": 30.24348594,
		"海拔高度/m": 49.113182,
		"树高度/m": 11.394734
	}, {
		"序号": 67,
		"模型编号": "Object794",
		"经度": 116.12547111,
		"纬度": 30.24855891,
		"海拔高度/m": 49.267948,
		"树高度/m": 4.031258
	}, {
		"序号": 68,
		"模型编号": "Object945",
		"经度": 116.11680342,
		"纬度": 30.28975714,
		"海拔高度/m": 49.361202,
		"树高度/m": 18.067484
	}, {
		"序号": 69,
		"模型编号": "Object927",
		"经度": 116.14497305,
		"纬度": 30.28824496,
		"海拔高度/m": 49.901077,
		"树高度/m": 10.745006
	}, {
		"序号": 70,
		"模型编号": "Object858",
		"经度": 116.07262975,
		"纬度": 30.23532357,
		"海拔高度/m": 50.105621,
		"树高度/m": 4.483998
	}, {
		"序号": 71,
		"模型编号": "Object1106",
		"经度": 116.0543045,
		"纬度": 30.21259356,
		"海拔高度/m": 50.139355,
		"树高度/m": 8.357014
	}, {
		"序号": 72,
		"模型编号": "Object929",
		"经度": 116.14257555,
		"纬度": 30.28904114,
		"海拔高度/m": 50.20108,
		"树高度/m": 5.004294
	}, {
		"序号": 73,
		"模型编号": "Object831",
		"经度": 116.08371614,
		"纬度": 30.24573447,
		"海拔高度/m": 50.913055,
		"树高度/m": 16.236362
	}, {
		"序号": 74,
		"模型编号": "Object1143",
		"经度": 116.08418575,
		"纬度": 30.24574397,
		"海拔高度/m": 50.913177,
		"树高度/m": 18.739516
	}, {
		"序号": 75,
		"模型编号": "Object1146",
		"经度": 116.07808358,
		"纬度": 30.24399228,
		"海拔高度/m": 50.913181,
		"树高度/m": 18.49111
	}, {
		"序号": 76,
		"模型编号": "Object1147",
		"经度": 116.07746889,
		"纬度": 30.24399299,
		"海拔高度/m": 50.913181,
		"树高度/m": 11.683568
	}, {
		"序号": 77,
		"模型编号": "Object1148",
		"经度": 116.07766897,
		"纬度": 30.2434361,
		"海拔高度/m": 50.913181,
		"树高度/m": 13.85305
	}, {
		"序号": 78,
		"模型编号": "Object877",
		"经度": 116.108086,
		"纬度": 30.24776174,
		"海拔高度/m": 51.209496,
		"树高度/m": 4.626658
	}, {
		"序号": 79,
		"模型编号": "Object860",
		"经度": 116.0696766,
		"纬度": 30.23082741,
		"海拔高度/m": 51.41848,
		"树高度/m": 14.872732
	}, {
		"序号": 80,
		"模型编号": "Object861",
		"经度": 116.0696001,
		"纬度": 30.23033477,
		"海拔高度/m": 51.41848,
		"树高度/m": 13.538214
	}, {
		"序号": 81,
		"模型编号": "Object932",
		"经度": 116.1383605,
		"纬度": 30.28903678,
		"海拔高度/m": 51.461212,
		"树高度/m": 10.207998
	}, {
		"序号": 82,
		"模型编号": "Object807",
		"经度": 116.12256834,
		"纬度": 30.24791567,
		"海拔高度/m": 51.920383,
		"树高度/m": 5.904288
	}, {
		"序号": 83,
		"模型编号": "Object830",
		"经度": 116.08351541,
		"纬度": 30.245954,
		"海拔高度/m": 52.113056,
		"树高度/m": 9.961016
	}, {
		"序号": 84,
		"模型编号": "Object928",
		"经度": 116.14475983,
		"纬度": 30.28792244,
		"海拔高度/m": 52.601078,
		"树高度/m": 9.021828
	}, {
		"序号": 85,
		"模型编号": "Object1152",
		"经度": 116.0754457,
		"纬度": 30.2419086,
		"海拔高度/m": 52.713188,
		"树高度/m": 12.436352
	}, {
		"序号": 86,
		"模型编号": "Object744",
		"经度": 116.13515622,
		"纬度": 30.24940354,
		"海拔高度/m": 52.894062,
		"树高度/m": 4.68862
	}, {
		"序号": 87,
		"模型编号": "Object743",
		"经度": 116.13515648,
		"纬度": 30.24903262,
		"海拔高度/m": 53.194061,
		"树高度/m": 3.601634
	}, {
		"序号": 88,
		"模型编号": "Object1154",
		"经度": 116.07298359,
		"纬度": 30.23558606,
		"海拔高度/m": 53.313187,
		"树高度/m": 11.520384
	}, {
		"序号": 89,
		"模型编号": "Object930",
		"经度": 116.14212164,
		"纬度": 30.28876622,
		"海拔高度/m": 53.561211,
		"树高度/m": 11.739478
	}, {
		"序号": 90,
		"模型编号": "Object796",
		"经度": 116.12518278,
		"纬度": 30.24848299,
		"海拔高度/m": 53.767948,
		"树高度/m": 9.573776
	}, {
		"序号": 91,
		"模型编号": "Object1142",
		"经度": 116.08448499,
		"纬度": 30.24532867,
		"海拔高度/m": 53.913177,
		"树高度/m": 18.397242
	}, {
		"序号": 92,
		"模型编号": "Object925",
		"经度": 116.14808834,
		"纬度": 30.28861596,
		"海拔高度/m": 53.952896,
		"树高度/m": 7.764868
	}, {
		"序号": 93,
		"模型编号": "Object791",
		"经度": 116.12578845,
		"纬度": 30.24821088,
		"海拔高度/m": 54.067947,
		"树高度/m": 5.682904
	}, {
		"序号": 94,
		"模型编号": "Object797",
		"经度": 116.12482134,
		"纬度": 30.24850122,
		"海拔高度/m": 54.067947,
		"树高度/m": 10.383652
	}, {
		"序号": 95,
		"模型编号": "Object1180",
		"经度": 116.05550883,
		"纬度": 30.2161382,
		"海拔高度/m": 54.136864,
		"树高度/m": 3.68562
	}, {
		"序号": 96,
		"模型编号": "Object1156",
		"经度": 116.07217609,
		"纬度": 30.23582978,
		"海拔高度/m": 54.213188,
		"树高度/m": 11.289626
	}, {
		"序号": 97,
		"模型编号": "Object1157",
		"经度": 116.06945966,
		"纬度": 30.23151882,
		"海拔高度/m": 54.213188,
		"树高度/m": 7.405918
	}, {
		"序号": 98,
		"模型编号": "Object783",
		"经度": 116.12672854,
		"纬度": 30.24793048,
		"海拔高度/m": 54.36795,
		"树高度/m": 5.693876
	}, {
		"序号": 99,
		"模型编号": "Object910",
		"经度": 116.05502089,
		"纬度": 30.21480448,
		"海拔高度/m": 54.391949,
		"树高度/m": 10.569766
	}, {
		"序号": 100,
		"模型编号": "Object1111",
		"经度": 116.05441912,
		"纬度": 30.21583932,
		"海拔高度/m": 54.489735,
		"树高度/m": 6.519706
	}, {
		"序号": 101,
		"模型编号": "Object782",
		"经度": 116.12720177,
		"纬度": 30.24777087,
		"海拔高度/m": 54.66795,
		"树高度/m": 5.260164
	}, {
		"序号": 102,
		"模型编号": "Object788",
		"经度": 116.1260901,
		"纬度": 30.248903,
		"海拔高度/m": 54.66795,
		"树高度/m": 14.30719
	}, {
		"序号": 103,
		"模型编号": "Object900",
		"经度": 116.0602408,
		"纬度": 30.22066324,
		"海拔高度/m": 54.691948,
		"树高度/m": 9.999988
	}, {
		"序号": 104,
		"模型编号": "Object1155",
		"经度": 116.07248134,
		"纬度": 30.23562459,
		"海拔高度/m": 54.813187,
		"树高度/m": 4.500648
	}, {
		"序号": 105,
		"模型编号": "Object716",
		"经度": 116.14695179,
		"纬度": 30.24896902,
		"海拔高度/m": 54.959633,
		"树高度/m": 3.827646
	}, {
		"序号": 106,
		"模型编号": "Object897",
		"经度": 116.056522,
		"纬度": 30.21836919,
		"海拔高度/m": 54.991951,
		"树高度/m": 4.481448
	}, {
		"序号": 107,
		"模型编号": "Object792",
		"经度": 116.12569395,
		"纬度": 30.24801558,
		"海拔高度/m": 55.267948,
		"树高度/m": 10.616108
	}, {
		"序号": 108,
		"模型编号": "Object715",
		"经度": 116.14745377,
		"纬度": 30.24924889,
		"海拔高度/m": 55.559631,
		"树高度/m": 3.231028
	}, {
		"序号": 109,
		"模型编号": "Object941",
		"经度": 116.13115613,
		"纬度": 30.28896114,
		"海拔高度/m": 55.661201,
		"树高度/m": 11.915234
	}, {
		"序号": 110,
		"模型编号": "Object1140",
		"经度": 116.12045633,
		"纬度": 30.24824999,
		"海拔高度/m": 55.713173,
		"树高度/m": 6.364436
	}, {
		"序号": 111,
		"模型编号": "Object717",
		"经度": 116.14655829,
		"纬度": 30.24887746,
		"海拔高度/m": 55.859634,
		"树高度/m": 5.964368
	}, {
		"序号": 112,
		"模型编号": "Object1137",
		"经度": 116.12210048,
		"纬度": 30.24917502,
		"海拔高度/m": 56.013168,
		"树高度/m": 10.780188
	}, {
		"序号": 113,
		"模型编号": "Object789",
		"经度": 116.12585463,
		"纬度": 30.2488239,
		"海拔高度/m": 56.16795,
		"树高度/m": 9.485072
	}, {
		"序号": 114,
		"模型编号": "Object1002",
		"经度": 116.06981028,
		"纬度": 30.30744639,
		"海拔高度/m": 56.202602,
		"树高度/m": 7.693902
	}, {
		"序号": 115,
		"模型编号": "Object942",
		"经度": 116.1304669,
		"纬度": 30.28940014,
		"海拔高度/m": 56.2612,
		"树高度/m": 13.92366
	}, {
		"序号": 116,
		"模型编号": "Object1150",
		"经度": 116.07585417,
		"纬度": 30.24185495,
		"海拔高度/m": 56.313187,
		"树高度/m": 18.903124
	}, {
		"序号": 117,
		"模型编号": "Object1159",
		"经度": 116.06883545,
		"纬度": 30.23004442,
		"海拔高度/m": 56.61319,
		"树高度/m": 18.11846
	}, {
		"序号": 118,
		"模型编号": "Object1104",
		"经度": 116.13148307,
		"纬度": 30.28968002,
		"海拔高度/m": 56.741409,
		"树高度/m": 11.331024
	}, {
		"序号": 119,
		"模型编号": "Object713",
		"经度": 116.14998053,
		"纬度": 30.24860106,
		"海拔高度/m": 56.759632,
		"树高度/m": 6.973058
	}, {
		"序号": 120,
		"模型编号": "Object786",
		"经度": 116.12677015,
		"纬度": 30.24851198,
		"海拔高度/m": 56.767952,
		"树高度/m": 9.473654
	}, {
		"序号": 121,
		"模型编号": "Object787",
		"经度": 116.12653672,
		"纬度": 30.24863134,
		"海拔高度/m": 56.767952,
		"树高度/m": 12.174218
	}, {
		"序号": 122,
		"模型编号": "Object894",
		"经度": 116.05804592,
		"纬度": 30.21714101,
		"海拔高度/m": 57.091957,
		"树高度/m": 11.422188
	}, {
		"序号": 123,
		"模型编号": "Object746",
		"经度": 116.13365232,
		"纬度": 30.24870922,
		"海拔高度/m": 57.094063,
		"树高度/m": 4.144458
	}, {
		"序号": 124,
		"模型编号": "Object938",
		"经度": 116.13253054,
		"纬度": 30.28943281,
		"海拔高度/m": 57.161201,
		"树高度/m": 6.728742
	}, {
		"序号": 125,
		"模型编号": "Object1153",
		"经度": 116.0738123,
		"纬度": 30.23666891,
		"海拔高度/m": 57.213188,
		"树高度/m": 15.46127
	}, {
		"序号": 126,
		"模型编号": "Object793",
		"经度": 116.12558289,
		"纬度": 30.2477375,
		"海拔高度/m": 57.367947,
		"树高度/m": 11.54614
	}, {
		"序号": 127,
		"模型编号": "Object909",
		"经度": 116.05530354,
		"纬度": 30.21420393,
		"海拔高度/m": 57.391945,
		"树高度/m": 15.825562
	}, {
		"序号": 128,
		"模型编号": "Object885",
		"经度": 116.05900788,
		"纬度": 30.21918959,
		"海拔高度/m": 57.655762,
		"树高度/m": 13.329274
	}, {
		"序号": 129,
		"模型编号": "Object1000",
		"经度": 116.07105907,
		"纬度": 30.30598698,
		"海拔高度/m": 57.702602,
		"树高度/m": 8.676322
	}, {
		"序号": 130,
		"模型编号": "Object931",
		"经度": 116.14187667,
		"纬度": 30.28892051,
		"海拔高度/m": 57.761211,
		"树高度/m": 16.515468
	}, {
		"序号": 131,
		"模型编号": "Object1141",
		"经度": 116.12088584,
		"纬度": 30.24856141,
		"海拔高度/m": 57.813175,
		"树高度/m": 15.230624
	}, {
		"序号": 132,
		"模型编号": "Object790",
		"经度": 116.1259346,
		"纬度": 30.24836105,
		"海拔高度/m": 57.967949,
		"树高度/m": 10.51861
	}, {
		"序号": 133,
		"模型编号": "Object905",
		"经度": 116.05604621,
		"纬度": 30.21745787,
		"海拔高度/m": 57.991943,
		"树高度/m": 5.419394
	}, {
		"序号": 134,
		"模型编号": "Object898",
		"经度": 116.05683067,
		"纬度": 30.21793256,
		"海拔高度/m": 57.991951,
		"树高度/m": 4.816802
	}, {
		"序号": 135,
		"模型编号": "Object924",
		"经度": 116.15242254,
		"纬度": 30.28796606,
		"海拔高度/m": 58.033009,
		"树高度/m": 6.157634
	}, {
		"序号": 136,
		"模型编号": "Object1181",
		"经度": 116.05598557,
		"纬度": 30.21658722,
		"海拔高度/m": 58.036865,
		"树高度/m": 6.347796
	}, {
		"序号": 137,
		"模型编号": "Object1015",
		"经度": 116.06753462,
		"纬度": 30.30858573,
		"海拔高度/m": 58.150833,
		"树高度/m": 9.973834
	}, {
		"序号": 138,
		"模型编号": "Object745",
		"经度": 116.13438004,
		"纬度": 30.24903676,
		"海拔高度/m": 58.294064,
		"树高度/m": 7.148042
	}, {
		"序号": 139,
		"模型编号": "Object695",
		"经度": 116.14182319,
		"纬度": 30.24896216,
		"海拔高度/m": 58.363846,
		"树高度/m": 3.425826
	}, {
		"序号": 140,
		"模型编号": "Object696",
		"经度": 116.14130169,
		"纬度": 30.24889956,
		"海拔高度/m": 58.363846,
		"树高度/m": 4.757568
	}, {
		"序号": 141,
		"模型编号": "Object1158",
		"经度": 116.06917631,
		"纬度": 30.23147098,
		"海拔高度/m": 58.413189,
		"树高度/m": 13.745068
	}, {
		"序号": 142,
		"模型编号": "Object1176",
		"经度": 116.05562164,
		"纬度": 30.21564846,
		"海拔高度/m": 58.828365,
		"树高度/m": 5.286918
	}, {
		"序号": 143,
		"模型编号": "Object712",
		"经度": 116.15068835,
		"纬度": 30.24961338,
		"海拔高度/m": 58.859631,
		"树高度/m": 4.29017
	}, {
		"序号": 144,
		"模型编号": "Object799",
		"经度": 116.12455309,
		"纬度": 30.24799388,
		"海拔高度/m": 58.867947,
		"树高度/m": 4.27148
	}, {
		"序号": 145,
		"模型编号": "Object933",
		"经度": 116.13802071,
		"纬度": 30.28860727,
		"海拔高度/m": 58.961212,
		"树高度/m": 19.138162
	}, {
		"序号": 146,
		"模型编号": "Object785",
		"经度": 116.12617514,
		"纬度": 30.24802071,
		"海拔高度/m": 59.167953,
		"树高度/m": 9.601242
	}, {
		"序号": 147,
		"模型编号": "Object742",
		"经度": 116.13579748,
		"纬度": 30.24888991,
		"海拔高度/m": 59.194061,
		"树高度/m": 4.635628
	}, {
		"序号": 148,
		"模型编号": "Object906",
		"经度": 116.05473017,
		"纬度": 30.21624953,
		"海拔高度/m": 59.491943,
		"树高度/m": 16.72851
	}, {
		"序号": 149,
		"模型编号": "Object693",
		"经度": 116.14147388,
		"纬度": 30.24864671,
		"海拔高度/m": 59.563843,
		"树高度/m": 5.279792
	}, {
		"序号": 150,
		"模型编号": "Object722",
		"经度": 116.14649244,
		"纬度": 30.24953676,
		"海拔高度/m": 59.681931,
		"树高度/m": 12.512926
	}, {
		"序号": 151,
		"模型编号": "Object740",
		"经度": 116.13792897,
		"纬度": 30.2489328,
		"海拔高度/m": 59.794064,
		"树高度/m": 5.953448
	}, {
		"序号": 152,
		"模型编号": "Object670",
		"经度": 116.13838718,
		"纬度": 30.24876679,
		"海拔高度/m": 59.863834,
		"树高度/m": 4.257628
	}, {
		"序号": 153,
		"模型编号": "Object697",
		"经度": 116.14095862,
		"纬度": 30.24886968,
		"海拔高度/m": 59.863846,
		"树高度/m": 5.805434
	}, {
		"序号": 154,
		"模型编号": "Object1134",
		"经度": 116.12566349,
		"纬度": 30.24851081,
		"海拔高度/m": 59.91317,
		"树高度/m": 12.179588
	}, {
		"序号": 155,
		"模型编号": "Object1135",
		"经度": 116.12443316,
		"纬度": 30.24878447,
		"海拔高度/m": 60.213169,
		"树高度/m": 17.28533
	}, {
		"序号": 156,
		"模型编号": "Object1136",
		"经度": 116.12379353,
		"纬度": 30.24860419,
		"海拔高度/m": 60.213169,
		"树高度/m": 12.75806
	}, {
		"序号": 157,
		"模型编号": "Object912",
		"经度": 116.05630091,
		"纬度": 30.21669421,
		"海拔高度/m": 60.395966,
		"树高度/m": 9.370162
	}, {
		"序号": 158,
		"模型编号": "Object911",
		"经度": 116.0564257,
		"纬度": 30.21776183,
		"海拔高度/m": 60.579971,
		"树高度/m": 11.395656
	}, {
		"序号": 159,
		"模型编号": "Object901",
		"经度": 116.05800301,
		"纬度": 30.21968037,
		"海拔高度/m": 60.691948,
		"树高度/m": 9.264164
	}, {
		"序号": 160,
		"模型编号": "Object812",
		"经度": 116.1230227,
		"纬度": 30.24878995,
		"海拔高度/m": 61.220387,
		"树高度/m": 8.754952
	}, {
		"序号": 161,
		"模型编号": "Object730",
		"经度": 116.13695799,
		"纬度": 30.24895098,
		"海拔高度/m": 61.294071,
		"树高度/m": 9.905396
	}, {
		"序号": 162,
		"模型编号": "Object947",
		"经度": 116.08399918,
		"纬度": 30.29574681,
		"海拔高度/m": 61.391811,
		"树高度/m": 9.552072
	}, {
		"序号": 163,
		"模型编号": "Object1169",
		"经度": 116.06434953,
		"纬度": 30.22439649,
		"海拔高度/m": 61.413193,
		"树高度/m": 9.545528
	}, {
		"序号": 164,
		"模型编号": "Object706",
		"经度": 116.14011337,
		"纬度": 30.24906119,
		"海拔高度/m": 61.559628,
		"树高度/m": 7.579508
	}, {
		"序号": 165,
		"模型编号": "Object801",
		"经度": 116.12382803,
		"纬度": 30.24770947,
		"海拔高度/m": 61.567947,
		"树高度/m": 4.936026
	}, {
		"序号": 166,
		"模型编号": "Object902",
		"经度": 116.05749933,
		"纬度": 30.21938377,
		"海拔高度/m": 61.591949,
		"树高度/m": 5.811314
	}, {
		"序号": 167,
		"模型编号": "Object689",
		"经度": 116.14317411,
		"纬度": 30.24849499,
		"海拔高度/m": 61.663845,
		"树高度/m": 4.903746
	}, {
		"序号": 168,
		"模型编号": "Object948",
		"经度": 116.08367901,
		"纬度": 30.29598133,
		"海拔高度/m": 61.691811,
		"树高度/m": 12.41611
	}, {
		"序号": 169,
		"模型编号": "Object721",
		"经度": 116.14494413,
		"纬度": 30.24881579,
		"海拔高度/m": 61.781929,
		"树高度/m": 6.337796
	}, {
		"序号": 170,
		"模型编号": "Object723",
		"经度": 116.14617401,
		"纬度": 30.24896354,
		"海拔高度/m": 61.781933,
		"树高度/m": 5.957064
	}, {
		"序号": 171,
		"模型编号": "Object819",
		"经度": 116.11962631,
		"纬度": 30.24827741,
		"海拔高度/m": 61.820381,
		"树高度/m": 4.788842
	}, {
		"序号": 172,
		"模型编号": "Object692",
		"经度": 116.14359847,
		"纬度": 30.24929681,
		"海拔高度/m": 61.963844,
		"树高度/m": 3.670132
	}, {
		"序号": 173,
		"模型编号": "Object1133",
		"经度": 116.1264628,
		"纬度": 30.24798545,
		"海拔高度/m": 62.013168,
		"树高度/m": 14.075126
	}, {
		"序号": 174,
		"模型编号": "Object767",
		"经度": 116.13120528,
		"纬度": 30.24789904,
		"海拔高度/m": 62.176231,
		"树高度/m": 7.402144
	}, {
		"序号": 175,
		"模型编号": "Object1114",
		"经度": 116.14366839,
		"纬度": 30.25005148,
		"海拔高度/m": 62.368172,
		"树高度/m": 11.321198
	}, {
		"序号": 176,
		"模型编号": "Object975",
		"经度": 116.07587194,
		"纬度": 30.30278255,
		"海拔高度/m": 62.502602,
		"树高度/m": 6.654552
	}, {
		"序号": 177,
		"模型编号": "Object939",
		"经度": 116.13234557,
		"纬度": 30.28892476,
		"海拔高度/m": 62.561203,
		"树高度/m": 8.913022
	}, {
		"序号": 178,
		"模型编号": "Object760",
		"经度": 116.13190606,
		"纬度": 30.24775955,
		"海拔高度/m": 62.77623,
		"树高度/m": 5.289694
	}, {
		"序号": 179,
		"模型编号": "Object699",
		"经度": 116.14041284,
		"纬度": 30.24869738,
		"海拔高度/m": 62.86385,
		"树高度/m": 5.4402
	}, {
		"序号": 180,
		"模型编号": "Object751",
		"经度": 116.13385824,
		"纬度": 30.2492216,
		"海拔高度/m": 62.939663,
		"树高度/m": 7.289774
	}, {
		"序号": 181,
		"模型编号": "Object725",
		"经度": 116.13916351,
		"纬度": 30.24914982,
		"海拔高度/m": 62.981934,
		"树高度/m": 12.01853
	}, {
		"序号": 182,
		"模型编号": "Object934",
		"经度": 116.13444291,
		"纬度": 30.28922737,
		"海拔高度/m": 63.161209,
		"树高度/m": 16.790344
	}, {
		"序号": 183,
		"模型编号": "Object671",
		"经度": 116.13812644,
		"纬度": 30.24851989,
		"海拔高度/m": 63.163834,
		"树高度/m": 3.776096
	}, {
		"序号": 184,
		"模型编号": "Object811",
		"经度": 116.1228569,
		"纬度": 30.24865478,
		"海拔高度/m": 63.320385,
		"树高度/m": 9.409856
	}, {
		"序号": 185,
		"模型编号": "Object707",
		"经度": 116.14038953,
		"纬度": 30.24922725,
		"海拔高度/m": 63.359627,
		"树高度/m": 4.868898
	}, {
		"序号": 186,
		"模型编号": "Object903",
		"经度": 116.057529,
		"纬度": 30.21897947,
		"海拔高度/m": 63.391949,
		"树高度/m": 7.626532
	}, {
		"序号": 187,
		"模型编号": "Object998",
		"经度": 116.07149043,
		"纬度": 30.3060405,
		"海拔高度/m": 63.702602,
		"树高度/m": 3.62941
	}, {
		"序号": 188,
		"模型编号": "Object1001",
		"经度": 116.06925665,
		"纬度": 30.30747742,
		"海拔高度/m": 63.702602,
		"树高度/m": 11.72652
	}, {
		"序号": 189,
		"模型编号": "Object698",
		"经度": 116.1408997,
		"纬度": 30.24866816,
		"海拔高度/m": 63.763847,
		"树高度/m": 4.751808
	}, {
		"序号": 191,
		"模型编号": "Object686",
		"经度": 116.14679771,
		"纬度": 30.24884027,
		"海拔高度/m": 64.063835,
		"树高度/m": 11.854404
	}, {
		"序号": 192,
		"模型编号": "Object690",
		"经度": 116.14230792,
		"纬度": 30.24877839,
		"海拔高度/m": 64.063843,
		"树高度/m": 10.950612
	}, {
		"序号": 193,
		"模型编号": "Object949",
		"经度": 116.08397825,
		"纬度": 30.2969538,
		"海拔高度/m": 64.091812,
		"树高度/m": 16.899432
	}, {
		"序号": 194,
		"模型编号": "Object1167",
		"经度": 116.06355233,
		"纬度": 30.22418971,
		"海拔高度/m": 64.11319,
		"树高度/m": 19.870212
	}, {
		"序号": 195,
		"模型编号": "Object1131",
		"经度": 116.12864266,
		"纬度": 30.24872186,
		"海拔高度/m": 64.41317,
		"树高度/m": 13.437208
	}, {
		"序号": 196,
		"模型编号": "Object1117",
		"经度": 116.13686985,
		"纬度": 30.24916052,
		"海拔高度/m": 64.46817,
		"树高度/m": 5.797994
	}, {
		"序号": 197,
		"模型编号": "Object727",
		"经度": 116.1386521,
		"纬度": 30.24931244,
		"海拔高度/m": 64.481934,
		"树高度/m": 10.485754
	}, {
		"序号": 198,
		"模型编号": "Object762",
		"经度": 116.13265459,
		"纬度": 30.24811013,
		"海拔高度/m": 64.576225,
		"树高度/m": 5.32879
	}, {
		"序号": 199,
		"模型编号": "Object1112",
		"经度": 116.14557609,
		"纬度": 30.24985888,
		"海拔高度/m": 64.833328,
		"树高度/m": 13.472782
	}, {
		"序号": 200,
		"模型编号": "Object1113",
		"经度": 116.14427471,
		"纬度": 30.24989345,
		"海拔高度/m": 64.833328,
		"树高度/m": 10.672016
	}, {
		"序号": 201,
		"模型编号": "Object979",
		"经度": 116.07467283,
		"纬度": 30.30360247,
		"海拔高度/m": 64.902603,
		"树高度/m": 5.831112
	}, {
		"序号": 202,
		"模型编号": "Object669",
		"经度": 116.13801886,
		"纬度": 30.2483991,
		"海拔高度/m": 64.963837,
		"树高度/m": 3.001292
	}, {
		"序号": 203,
		"模型编号": "Object1118",
		"经度": 116.13605116,
		"纬度": 30.24873315,
		"海拔高度/m": 65.068169,
		"树高度/m": 6.695698
	}, {
		"序号": 204,
		"模型编号": "Object1067",
		"经度": 116.05342606,
		"纬度": 30.3202626,
		"海拔高度/m": 65.091469,
		"树高度/m": 10.315042
	}, {
		"序号": 205,
		"模型编号": "Object741",
		"经度": 116.13534997,
		"纬度": 30.24886995,
		"海拔高度/m": 65.194061,
		"树高度/m": 8.306106
	}, {
		"序号": 206,
		"模型编号": "Object976",
		"经度": 116.07527392,
		"纬度": 30.30321404,
		"海拔高度/m": 65.202599,
		"树高度/m": 5.67537
	}, {
		"序号": 207,
		"模型编号": "Object935",
		"经度": 116.13452144,
		"纬度": 30.28888985,
		"海拔高度/m": 65.261208,
		"树高度/m": 18.579642
	}, {
		"序号": 208,
		"模型编号": "Object687",
		"经度": 116.14792039,
		"纬度": 30.24833196,
		"海拔高度/m": 65.26384,
		"树高度/m": 3.449162
	}, {
		"序号": 209,
		"模型编号": "Object764",
		"经度": 116.13317306,
		"纬度": 30.24897143,
		"海拔高度/m": 65.476227,
		"树高度/m": 6.099958
	}, {
		"序号": 210,
		"模型编号": "Object728",
		"经度": 116.13800166,
		"纬度": 30.24930742,
		"海拔高度/m": 65.494072,
		"树高度/m": 5.559238
	}, {
		"序号": 211,
		"模型编号": "Object950",
		"经度": 116.08319148,
		"纬度": 30.29746551,
		"海拔高度/m": 65.591805,
		"树高度/m": 19.700278
	}, {
		"序号": 212,
		"模型编号": "Object968",
		"经度": 116.07698416,
		"纬度": 30.30200069,
		"海拔高度/m": 65.591812,
		"树高度/m": 4.78579
	}, {
		"序号": 213,
		"模型编号": "Object1132",
		"经度": 116.12866212,
		"纬度": 30.24887579,
		"海拔高度/m": 65.613167,
		"树高度/m": 9.617686
	}, {
		"序号": 214,
		"模型编号": "Object1123",
		"经度": 116.14162059,
		"纬度": 30.24995997,
		"海拔高度/m": 65.613182,
		"树高度/m": 9.00021
	}, {
		"序号": 215,
		"模型编号": "Object1124",
		"经度": 116.13971411,
		"纬度": 30.24892203,
		"海拔高度/m": 65.613182,
		"树高度/m": 7.96512
	}, {
		"序号": 216,
		"模型编号": "Object719",
		"经度": 116.13899354,
		"纬度": 30.24883331,
		"海拔高度/m": 65.681931,
		"树高度/m": 11.615334
	}, {
		"序号": 217,
		"模型编号": "Object915",
		"经度": 116.15514496,
		"纬度": 30.28833229,
		"海拔高度/m": 65.795967,
		"树高度/m": 7.585274
	}, {
		"序号": 218,
		"模型编号": "Object678",
		"经度": 116.14211651,
		"纬度": 30.24850278,
		"海拔高度/m": 65.863831,
		"树高度/m": 5.83974
	}, {
		"序号": 219,
		"模型编号": "Object684",
		"经度": 116.14604626,
		"纬度": 30.24856868,
		"海拔高度/m": 65.863838,
		"树高度/m": 3.195076
	}, {
		"序号": 220,
		"模型编号": "Object688",
		"经度": 116.14438294,
		"纬度": 30.24857712,
		"海拔高度/m": 65.863846,
		"树高度/m": 9.76689
	}, {
		"序号": 221,
		"模型编号": "Object1115",
		"经度": 116.14272801,
		"纬度": 30.24948492,
		"海拔高度/m": 65.96817,
		"树高度/m": 14.431034
	}, {
		"序号": 222,
		"模型编号": "Object1025",
		"经度": 116.06325308,
		"纬度": 30.3118259,
		"海拔高度/m": 66.084488,
		"树高度/m": 4.053632
	}, {
		"序号": 223,
		"模型编号": "Object893",
		"经度": 116.05766304,
		"纬度": 30.21707604,
		"海拔高度/m": 66.091957,
		"树高度/m": 15.75384
	}, {
		"序号": 224,
		"模型编号": "Object729",
		"经度": 116.13740138,
		"纬度": 30.2496602,
		"海拔高度/m": 66.09407,
		"树高度/m": 3.357982
	}, {
		"序号": 225,
		"模型编号": "Object991",
		"经度": 116.07323335,
		"纬度": 30.3050506,
		"海拔高度/m": 66.1026,
		"树高度/m": 5.395784
	}, {
		"序号": 226,
		"模型编号": "Object1139",
		"经度": 116.12215111,
		"纬度": 30.24863478,
		"海拔高度/m": 66.213173,
		"树高度/m": 12.846818
	}, {
		"序号": 227,
		"模型编号": "Object1192",
		"经度": 116.07256663,
		"纬度": 30.30478912,
		"海拔高度/m": 66.266426,
		"树高度/m": 5.559236
	}, {
		"序号": 228,
		"模型编号": "Object708",
		"经度": 116.14027402,
		"纬度": 30.24970263,
		"海拔高度/m": 66.359627,
		"树高度/m": 9.097924
	}, {
		"序号": 229,
		"模型编号": "Object761",
		"经度": 116.13243794,
		"纬度": 30.2479876,
		"海拔高度/m": 66.376228,
		"树高度/m": 6.935176
	}, {
		"序号": 230,
		"模型编号": "Object1026",
		"经度": 116.06398918,
		"纬度": 30.31150575,
		"海拔高度/m": 66.384491,
		"树高度/m": 4.580766
	}, {
		"序号": 231,
		"模型编号": "Object1173",
		"经度": 116.05607524,
		"纬度": 30.21540281,
		"海拔高度/m": 66.513184,
		"树高度/m": 19.090192
	}, {
		"序号": 232,
		"模型编号": "Object726",
		"经度": 116.13925419,
		"纬度": 30.24976526,
		"海拔高度/m": 66.581932,
		"树高度/m": 8.471344
	}, {
		"序号": 233,
		"模型编号": "Object685",
		"经度": 116.14631921,
		"纬度": 30.24850681,
		"海拔高度/m": 66.76384,
		"树高度/m": 10.889522
	}, {
		"序号": 234,
		"模型编号": "Object1027",
		"经度": 116.06413197,
		"纬度": 30.31202483,
		"海拔高度/m": 66.984489,
		"树高度/m": 10.808548
	}, {
		"序号": 235,
		"模型编号": "Object918",
		"经度": 116.15431144,
		"纬度": 30.28821431,
		"海拔高度/m": 66.986145,
		"树高度/m": 9.94638
	}, {
		"序号": 236,
		"模型编号": "Object732",
		"经度": 116.13699594,
		"纬度": 30.24841008,
		"海拔高度/m": 66.994064,
		"树高度/m": 6.063334
	}, {
		"序号": 237,
		"模型编号": "Object1021",
		"经度": 116.06516098,
		"纬度": 30.31076918,
		"海拔高度/m": 67.093781,
		"树高度/m": 6.818832
	}, {
		"序号": 238,
		"模型编号": "Object1172",
		"经度": 116.05558944,
		"纬度": 30.21525537,
		"海拔高度/m": 67.113182,
		"树高度/m": 17.114886
	}, {
		"序号": 239,
		"模型编号": "Object1186",
		"经度": 116.1332195,
		"纬度": 30.28943636,
		"海拔高度/m": 67.337006,
		"树高度/m": 19.26816
	}, {
		"序号": 241,
		"模型编号": "Object955",
		"经度": 116.08103303,
		"纬度": 30.29871735,
		"海拔高度/m": 67.391808,
		"树高度/m": 15.043232
	}, {
		"序号": 242,
		"模型编号": "Object1128",
		"经度": 116.13059561,
		"纬度": 30.24873757,
		"海拔高度/m": 67.713173,
		"树高度/m": 6.960114
	}, {
		"序号": 243,
		"模型编号": "Object1193",
		"经度": 116.07225346,
		"纬度": 30.30567993,
		"海拔高度/m": 67.766426,
		"树高度/m": 6.952352
	}, {
		"序号": 244,
		"模型编号": "Object700",
		"经度": 116.14070549,
		"纬度": 30.24901429,
		"海拔高度/m": 68.263847,
		"树高度/m": 14.581582
	}, {
		"序号": 245,
		"模型编号": "Object1177",
		"经度": 116.05546785,
		"纬度": 30.21666372,
		"海拔高度/m": 68.428368,
		"树高度/m": 6.799036
	}, {
		"序号": 246,
		"模型编号": "Object768",
		"经度": 116.13127465,
		"纬度": 30.2480913,
		"海拔高度/m": 68.467957,
		"树高度/m": 7.506378
	}, {
		"序号": 247,
		"模型编号": "Object977",
		"经度": 116.07567076,
		"纬度": 30.30310606,
		"海拔高度/m": 68.502602,
		"树高度/m": 6.680094
	}, {
		"序号": 248,
		"模型编号": "Object1122",
		"经度": 116.14502673,
		"纬度": 30.24924619,
		"海拔高度/m": 68.613182,
		"树高度/m": 14.767858
	}, {
		"序号": 249,
		"模型编号": "Object765",
		"经度": 116.13137226,
		"纬度": 30.24776767,
		"海拔高度/m": 68.77623,
		"树高度/m": 13.816096
	}, {
		"序号": 250,
		"模型编号": "Object679",
		"经度": 116.14282168,
		"纬度": 30.24866645,
		"海拔高度/m": 68.863831,
		"树高度/m": 11.385848
	}, {
		"序号": 251,
		"模型编号": "Object1138",
		"经度": 116.12295065,
		"纬度": 30.24813182,
		"海拔高度/m": 68.91317,
		"树高度/m": 8.333132
	}, {
		"序号": 252,
		"模型编号": "Object990",
		"经度": 116.07272167,
		"纬度": 30.30537763,
		"海拔高度/m": 69.1026,
		"树高度/m": 4.1551
	}, {
		"序号": 253,
		"模型编号": "Object1191",
		"经度": 116.07364623,
		"纬度": 30.30414655,
		"海拔高度/m": 69.266426,
		"树高度/m": 6.544744
	}, {
		"序号": 254,
		"模型编号": "Object766",
		"经度": 116.13142443,
		"纬度": 30.24785887,
		"海拔高度/m": 69.376228,
		"树高度/m": 9.003282
	}, {
		"序号": 255,
		"模型编号": "Object1182",
		"经度": 116.05719417,
		"纬度": 30.2184714,
		"海拔高度/m": 69.436867,
		"树高度/m": 9.257202
	}, {
		"序号": 256,
		"模型编号": "Object919",
		"经度": 116.15357756,
		"纬度": 30.2877827,
		"海拔高度/m": 69.733139,
		"树高度/m": 13.981882
	}, {
		"序号": 257,
		"模型编号": "Object1185",
		"经度": 116.1328301,
		"纬度": 30.28878185,
		"海拔高度/m": 69.737,
		"树高度/m": 10.22523
	}, {
		"序号": 258,
		"模型编号": "Object937",
		"经度": 116.13453064,
		"纬度": 30.289434,
		"海拔高度/m": 70.061203,
		"树高度/m": 19.330732
	}, {
		"序号": 259,
		"模型编号": "Object1127",
		"经度": 116.13134952,
		"纬度": 30.24857714,
		"海拔高度/m": 70.413177,
		"树高度/m": 11.566168
	}, {
		"序号": 260,
		"模型编号": "Object755",
		"经度": 116.13392922,
		"纬度": 30.24809333,
		"海拔高度/m": 70.50724,
		"树高度/m": 3.099312
	}, {
		"序号": 261,
		"模型编号": "Object1178",
		"经度": 116.05635161,
		"纬度": 30.21728116,
		"海拔高度/m": 70.936867,
		"树高度/m": 7.085694
	}, {
		"序号": 262,
		"模型编号": "Object733",
		"经度": 116.13706868,
		"纬度": 30.24821774,
		"海拔高度/m": 71.494064,
		"树高度/m": 3.089908
	}, {
		"序号": 263,
		"模型编号": "Object993",
		"经度": 116.07173321,
		"纬度": 30.30531803,
		"海拔高度/m": 71.502602,
		"树高度/m": 3.479904
	}, {
		"序号": 264,
		"模型编号": "Object996",
		"经度": 116.0713989,
		"纬度": 30.30574499,
		"海拔高度/m": 71.502602,
		"树高度/m": 10.516128
	}, {
		"序号": 265,
		"模型编号": "Object1187",
		"经度": 116.08007596,
		"纬度": 30.29956526,
		"海拔高度/m": 71.966423,
		"树高度/m": 3.133946
	}, {
		"序号": 266,
		"模型编号": "Object887",
		"经度": 116.05928226,
		"纬度": 30.2198381,
		"海拔高度/m": 72.055756,
		"树高度/m": 14.346158
	}, {
		"序号": 267,
		"模型编号": "Object773",
		"经度": 116.12920634,
		"纬度": 30.24814211,
		"海拔高度/m": 72.067955,
		"树高度/m": 4.615618
	}, {
		"序号": 268,
		"模型编号": "Object890",
		"经度": 116.05947466,
		"纬度": 30.21906067,
		"海拔高度/m": 72.091965,
		"树高度/m": 15.933964
	}, {
		"序号": 269,
		"模型编号": "Object1092",
		"经度": 116.04252536,
		"纬度": 30.32860303,
		"海拔高度/m": 72.100677,
		"树高度/m": 6.439326
	}, {
		"序号": 270,
		"模型编号": "Object1028",
		"经度": 116.06531174,
		"纬度": 30.311124,
		"海拔高度/m": 72.384491,
		"树高度/m": 7.625368
	}, {
		"序号": 271,
		"模型编号": "Object776",
		"经度": 116.12993337,
		"纬度": 30.24840681,
		"海拔高度/m": 72.967957,
		"树高度/m": 8.315028
	}, {
		"序号": 272,
		"模型编号": "Object956",
		"经度": 116.08088189,
		"纬度": 30.29925037,
		"海拔高度/m": 73.091812,
		"树高度/m": 5.209688
	}, {
		"序号": 273,
		"模型编号": "Object952",
		"经度": 116.08177602,
		"纬度": 30.298322,
		"海拔高度/m": 73.391808,
		"树高度/m": 14.0676
	}, {
		"序号": 274,
		"模型编号": "Object953",
		"经度": 116.08163445,
		"纬度": 30.29854205,
		"海拔高度/m": 73.391808,
		"树高度/m": 13.194906
	}, {
		"序号": 275,
		"模型编号": "Object1119",
		"经度": 116.13665318,
		"纬度": 30.24848431,
		"海拔高度/m": 73.46817,
		"树高度/m": 7.273722
	}, {
		"序号": 276,
		"模型编号": "Object1022",
		"经度": 116.06465507,
		"纬度": 30.31085445,
		"海拔高度/m": 73.693779,
		"树高度/m": 8.16706
	}, {
		"序号": 277,
		"模型编号": "Object1023",
		"经度": 116.0645862,
		"纬度": 30.31157455,
		"海拔高度/m": 73.693779,
		"树高度/m": 4.678242
	}, {
		"序号": 278,
		"模型编号": "Object1077",
		"经度": 116.05005605,
		"纬度": 30.32213352,
		"海拔高度/m": 73.711998,
		"树高度/m": 9.840154
	}, {
		"序号": 279,
		"模型编号": "Object1078",
		"经度": 116.04954581,
		"纬度": 30.32246447,
		"海拔高度/m": 74.012001,
		"树高度/m": 14.952282
	}, {
		"序号": 280,
		"模型编号": "Object921",
		"经度": 116.15626567,
		"纬度": 30.28820711,
		"海拔高度/m": 74.233009,
		"树高度/m": 4.723964
	}, {
		"序号": 281,
		"模型编号": "Object960",
		"经度": 116.07977241,
		"纬度": 30.2997658,
		"海拔高度/m": 74.291809,
		"树高度/m": 4.273064
	}, {
		"序号": 282,
		"模型编号": "Object963",
		"经度": 116.07926289,
		"纬度": 30.29985481,
		"海拔高度/m": 74.291817,
		"树高度/m": 6.390424
	}, {
		"序号": 283,
		"模型编号": "Object964",
		"经度": 116.07926301,
		"纬度": 30.30029813,
		"海拔高度/m": 74.291817,
		"树高度/m": 7.949878
	}, {
		"序号": 284,
		"模型编号": "Object777",
		"经度": 116.12970228,
		"纬度": 30.24799651,
		"海拔高度/m": 74.467949,
		"树高度/m": 4.544474
	}, {
		"序号": 285,
		"模型编号": "Object756",
		"经度": 116.1367801,
		"纬度": 30.24801244,
		"海拔高度/m": 75.007248,
		"树高度/m": 6.049852
	}, {
		"序号": 286,
		"模型编号": "Object1032",
		"经度": 116.06211982,
		"纬度": 30.31252862,
		"海拔高度/m": 75.084488,
		"树高度/m": 9.167536
	}, {
		"序号": 287,
		"模型编号": "Object1004",
		"经度": 116.06919833,
		"纬度": 30.30805403,
		"海拔高度/m": 75.1026,
		"树高度/m": 8.839528
	}, {
		"序号": 288,
		"模型编号": "Object1170",
		"经度": 116.06051776,
		"纬度": 30.22011148,
		"海拔高度/m": 75.213188,
		"树高度/m": 19.013202
	}, {
		"序号": 289,
		"模型编号": "Object752",
		"经度": 116.13262616,
		"纬度": 30.24785445,
		"海拔高度/m": 75.539665,
		"树高度/m": 12.72085
	}, {
		"序号": 290,
		"模型编号": "Object753",
		"经度": 116.13239365,
		"纬度": 30.24768158,
		"海拔高度/m": 75.539665,
		"树高度/m": 13.973106
	}, {
		"序号": 291,
		"模型编号": "Object1068",
		"经度": 116.0504078,
		"纬度": 30.32186608,
		"海拔高度/m": 75.591469,
		"树高度/m": 5.043972
	}, {
		"序号": 292,
		"模型编号": "Object1038",
		"经度": 116.05648338,
		"纬度": 30.3179034,
		"海拔高度/m": 75.684494,
		"树高度/m": 12.577358
	}, {
		"序号": 294,
		"模型编号": "Object957",
		"经度": 116.08060983,
		"纬度": 30.29938676,
		"海拔高度/m": 75.791817,
		"树高度/m": 7.843848
	}, {
		"序号": 295,
		"模型编号": "Object1129",
		"经度": 116.13079601,
		"纬度": 30.24851526,
		"海拔高度/m": 76.113174,
		"树高度/m": 12.791818
	}, {
		"序号": 296,
		"模型编号": "Object972",
		"经度": 116.07738478,
		"纬度": 30.30176478,
		"海拔高度/m": 76.302605,
		"树高度/m": 6.347896
	}, {
		"序号": 297,
		"模型编号": "Object981",
		"经度": 116.07433857,
		"纬度": 30.30391849,
		"海拔高度/m": 76.302605,
		"树高度/m": 4.93146
	}, {
		"序号": 298,
		"模型编号": "Object895",
		"经度": 116.05816104,
		"纬度": 30.21808634,
		"海拔高度/m": 76.891953,
		"树高度/m": 11.227794
	}, {
		"序号": 299,
		"模型编号": "Object995",
		"经度": 116.07134442,
		"纬度": 30.30541154,
		"海拔高度/m": 76.902603,
		"树高度/m": 10.698182
	}, {
		"序号": 300,
		"模型编号": "Object961",
		"经度": 116.07991865,
		"纬度": 30.29894777,
		"海拔高度/m": 76.991806,
		"树高度/m": 3.402608
	}, {
		"序号": 301,
		"模型编号": "Object962",
		"经度": 116.07913384,
		"纬度": 30.30061049,
		"海拔高度/m": 76.991806,
		"树高度/m": 14.72801
	}, {
		"序号": 302,
		"模型编号": "Object922",
		"经度": 116.15544916,
		"纬度": 30.28797475,
		"海拔高度/m": 77.233009,
		"树高度/m": 11.569862
	}, {
		"序号": 303,
		"模型编号": "Object1130",
		"经度": 116.12952996,
		"纬度": 30.24854926,
		"海拔高度/m": 77.313171,
		"树高度/m": 10.621488
	}, {
		"序号": 304,
		"模型编号": "Object889",
		"经度": 116.0591402,
		"纬度": 30.2183705,
		"海拔高度/m": 77.491966,
		"树高度/m": 5.01428
	}, {
		"序号": 305,
		"模型编号": "Object973",
		"经度": 116.07744558,
		"纬度": 30.30186645,
		"海拔高度/m": 77.502602,
		"树高度/m": 11.683442
	}, {
		"序号": 306,
		"模型编号": "Object1006",
		"经度": 116.0685497,
		"纬度": 30.30765263,
		"海拔高度/m": 77.802597,
		"树高度/m": 15.17051
	}, {
		"序号": 307,
		"模型编号": "Object920",
		"经度": 116.15591193,
		"纬度": 30.2876757,
		"海拔高度/m": 77.833008,
		"树高度/m": 12.122052
	}, {
		"序号": 308,
		"模型编号": "Object954",
		"经度": 116.08157405,
		"纬度": 30.29872943,
		"海拔高度/m": 77.891808,
		"树高度/m": 14.983202
	}, {
		"序号": 309,
		"模型编号": "Object896",
		"经度": 116.05870224,
		"纬度": 30.21851243,
		"海拔高度/m": 78.091949,
		"树高度/m": 5.083882
	}, {
		"序号": 310,
		"模型编号": "Object1125",
		"经度": 116.13542108,
		"纬度": 30.24847522,
		"海拔高度/m": 78.213181,
		"树高度/m": 7.060638
	}, {
		"序号": 311,
		"模型编号": "Object958",
		"经度": 116.08029337,
		"纬度": 30.29883188,
		"海拔高度/m": 78.491814,
		"树高度/m": 10.217108
	}, {
		"序号": 312,
		"模型编号": "Object1194",
		"经度": 116.06824973,
		"纬度": 30.30883748,
		"海拔高度/m": 78.566429,
		"树高度/m": 4.684242
	}, {
		"序号": 313,
		"模型编号": "Object1184",
		"经度": 116.15415964,
		"纬度": 30.28778107,
		"海拔高度/m": 79.637001,
		"树高度/m": 11.945466
	}, {
		"序号": 314,
		"模型编号": "Object1014",
		"经度": 116.06771606,
		"纬度": 30.30844161,
		"海拔高度/m": 79.750832,
		"树高度/m": 14.486594
	}, {
		"序号": 315,
		"模型编号": "Object1195",
		"经度": 116.06845471,
		"纬度": 30.30821861,
		"海拔高度/m": 79.766426,
		"树高度/m": 8.471816
	}, {
		"序号": 316,
		"模型编号": "Object1212",
		"经度": 116.05643574,
		"纬度": 30.31673878,
		"海拔高度/m": 80.129356,
		"树高度/m": 3.8905
	}, {
		"序号": 317,
		"模型编号": "Object1213",
		"经度": 116.05669335,
		"纬度": 30.31698254,
		"海拔高度/m": 80.129356,
		"树高度/m": 10.097912
	}, {
		"序号": 318,
		"模型编号": "Object974",
		"经度": 116.07778465,
		"纬度": 30.30139267,
		"海拔高度/m": 80.202599,
		"树高度/m": 3.065084
	}, {
		"序号": 319,
		"模型编号": "Object1005",
		"经度": 116.06871454,
		"纬度": 30.30840579,
		"海拔高度/m": 80.202599,
		"树高度/m": 14.62806
	}, {
		"序号": 320,
		"模型编号": "Object1030",
		"经度": 116.06246662,
		"纬度": 30.31231326,
		"海拔高度/m": 80.484489,
		"树高度/m": 14.281522
	}, {
		"序号": 321,
		"模型编号": "Object878",
		"经度": 116.10909241,
		"纬度": 30.24783645,
		"海拔高度/m": 80.569153,
		"树高度/m": 16.087946
	}, {
		"序号": 322,
		"模型编号": "Object1012",
		"经度": 116.06789572,
		"纬度": 30.30923244,
		"海拔高度/m": 80.650833,
		"树高度/m": 12.021884
	}, {
		"序号": 323,
		"模型编号": "Object983",
		"经度": 116.07407337,
		"纬度": 30.30430102,
		"海拔高度/m": 80.802605,
		"树高度/m": 9.255208
	}, {
		"序号": 324,
		"模型编号": "Object757",
		"经度": 116.13516235,
		"纬度": 30.24802967,
		"海拔高度/m": 80.846832,
		"树高度/m": 16.778722
	}, {
		"序号": 325,
		"模型编号": "Object1188",
		"经度": 116.07945188,
		"纬度": 30.29929493,
		"海拔高度/m": 80.966423,
		"树高度/m": 8.877834
	}, {
		"序号": 326,
		"模型编号": "Object1196",
		"经度": 116.06783039,
		"纬度": 30.30893108,
		"海拔高度/m": 80.966423,
		"树高度/m": 11.636582
	}, {
		"序号": 327,
		"模型编号": "Object1029",
		"经度": 116.06309787,
		"纬度": 30.31251181,
		"海拔高度/m": 81.084488,
		"树高度/m": 14.733838
	}, {
		"序号": 328,
		"模型编号": "Object1008",
		"经度": 116.06880997,
		"纬度": 30.30792623,
		"海拔高度/m": 81.102592,
		"树高度/m": 18.3699
	}, {
		"序号": 329,
		"模型编号": "Object1183",
		"经度": 116.15540155,
		"纬度": 30.28764757,
		"海拔高度/m": 81.436996,
		"树高度/m": 8.74715
	}, {
		"序号": 330,
		"模型编号": "Object1214",
		"经度": 116.05721844,
		"纬度": 30.31690113,
		"海拔高度/m": 81.629356,
		"树高度/m": 11.479128
	}, {
		"序号": 331,
		"模型编号": "Object1031",
		"经度": 116.06251998,
		"纬度": 30.31259718,
		"海拔高度/m": 81.984489,
		"树高度/m": 14.894398
	}, {
		"序号": 332,
		"模型编号": "Object1033",
		"经度": 116.06230577,
		"纬度": 30.31325355,
		"海拔高度/m": 81.984489,
		"树高度/m": 10.167152
	}, {
		"序号": 333,
		"模型编号": "Object1034",
		"经度": 116.06217731,
		"纬度": 30.31336301,
		"海拔高度/m": 81.984489,
		"树高度/m": 12.095804
	}, {
		"序号": 334,
		"模型编号": "Object1035",
		"经度": 116.06184982,
		"纬度": 30.31280378,
		"海拔高度/m": 81.984489,
		"树高度/m": 11.668328
	}, {
		"序号": 335,
		"模型编号": "Object1024",
		"经度": 116.06358233,
		"纬度": 30.31149168,
		"海拔高度/m": 82.393784,
		"树高度/m": 6.137522
	}, {
		"序号": 336,
		"模型编号": "Object1166",
		"经度": 116.06401554,
		"纬度": 30.22376213,
		"海拔高度/m": 83.313187,
		"树高度/m": 5.253136
	}, {
		"序号": 337,
		"模型编号": "Object1020",
		"经度": 116.06527776,
		"纬度": 30.31023289,
		"海拔高度/m": 83.650833,
		"树高度/m": 14.86163
	}, {
		"序号": 338,
		"模型编号": "Object880",
		"经度": 116.10982728,
		"纬度": 30.24726104,
		"海拔高度/m": 83.677734,
		"树高度/m": 13.206652
	}, {
		"序号": 339,
		"模型编号": "Object967",
		"经度": 116.07775936,
		"纬度": 30.30054121,
		"海拔高度/m": 83.891815,
		"树高度/m": 4.464154
	}, {
		"序号": 340,
		"模型编号": "Object1190",
		"经度": 116.07546077,
		"纬度": 30.30335135,
		"海拔高度/m": 83.966431,
		"树高度/m": 13.772084
	}, {
		"序号": 341,
		"模型编号": "Object1013",
		"经度": 116.06808735,
		"纬度": 30.30798726,
		"海拔高度/m": 84.250832,
		"树高度/m": 18.822632
	}, {
		"序号": 342,
		"模型编号": "Object1036",
		"经度": 116.06183364,
		"纬度": 30.31373623,
		"海拔高度/m": 85.284492,
		"树高度/m": 6.302636
	}, {
		"序号": 343,
		"模型编号": "Object881",
		"经度": 116.10849189,
		"纬度": 30.24704278,
		"海拔高度/m": 85.477737,
		"树高度/m": 18.850438
	}, {
		"序号": 344,
		"模型编号": "Object1070",
		"经度": 116.04971385,
		"纬度": 30.32282061,
		"海拔高度/m": 85.49147,
		"树高度/m": 12.452676
	}, {
		"序号": 345,
		"模型编号": "Object1211",
		"经度": 116.05751599,
		"纬度": 30.3167958,
		"海拔高度/m": 85.52935,
		"树高度/m": 9.13695
	}, {
		"序号": 346,
		"模型编号": "Object1019",
		"经度": 116.06495109,
		"纬度": 30.31040867,
		"海拔高度/m": 86.35083,
		"树高度/m": 13.748268
	}, {
		"序号": 347,
		"模型编号": "Object882",
		"经度": 116.06373774,
		"纬度": 30.22363056,
		"海拔高度/m": 87.877739,
		"树高度/m": 15.105714
	}, {
		"序号": 348,
		"模型编号": "Object1120",
		"经度": 116.13625461,
		"纬度": 30.24811105,
		"海拔高度/m": 88.113182,
		"树高度/m": 16.151436
	}, {
		"序号": 349,
		"模型编号": "Object1126",
		"经度": 116.13347858,
		"纬度": 30.24780566,
		"海拔高度/m": 91.113174,
		"树高度/m": 16.32537
	}, {
		"序号": 350,
		"模型编号": "Object1189",
		"经度": 116.07670224,
		"纬度": 30.3015283,
		"海拔高度/m": 91.166428,
		"树高度/m": 13.138384
	}, {
		"序号": 351,
		"模型编号": "Object1121",
		"经度": 116.13564247,
		"纬度": 30.24817831,
		"海拔高度/m": 91.713181,
		"树高度/m": 17.301306
	}, {
		"序号": 352,
		"模型编号": "Object1093",
		"经度": 116.04192674,
		"纬度": 30.32889292,
		"海拔高度/m": 92.200676,
		"树高度/m": 14.517266
	}, {
		"序号": 353,
		"模型编号": "Object1043",
		"经度": 116.05842628,
		"纬度": 30.31637203,
		"海拔高度/m": 92.329292,
		"树高度/m": 3.189882
	}, {
		"序号": 354,
		"模型编号": "Object1209",
		"经度": 116.05699258,
		"纬度": 30.3164806,
		"海拔高度/m": 93.02935,
		"树高度/m": 7.141078
	}, {
		"序号": 355,
		"模型编号": "Object1215",
		"经度": 116.04854828,
		"纬度": 30.3238363,
		"海拔高度/m": 93.02935,
		"树高度/m": 9.324204
	}, {
		"序号": 356,
		"模型编号": "Object1226",
		"经度": 116.04139316,
		"纬度": 30.32879113,
		"海拔高度/m": 93.066223,
		"树高度/m": 12.187232
	}, {
		"序号": 357,
		"模型编号": "Object1079",
		"经度": 116.04828387,
		"纬度": 30.32330591,
		"海拔高度/m": 93.121429,
		"树高度/m": 3.828492
	}, {
		"序号": 358,
		"模型编号": "Object1210",
		"经度": 116.05772715,
		"纬度": 30.31632436,
		"海拔高度/m": 94.229355,
		"树高度/m": 10.784734
	}, {
		"序号": 359,
		"模型编号": "Object1076",
		"经度": 116.03651752,
		"纬度": 30.33249752,
		"海拔高度/m": 96.957764,
		"树高度/m": 12.692188
	}, {
		"序号": 360,
		"模型编号": "Object1197",
		"经度": 116.06148077,
		"纬度": 30.31329889,
		"海拔高度/m": 97.63797,
		"树高度/m": 7.967612
	}, {
		"序号": 361,
		"模型编号": "Object1102",
		"经度": 116.04040268,
		"纬度": 30.32932553,
		"海拔高度/m": 99.379211,
		"树高度/m": 19.9482
	}, {
		"序号": 362,
		"模型编号": "Object1199",
		"经度": 116.06146984,
		"纬度": 30.31359929,
		"海拔高度/m": 100.602943,
		"树高度/m": 10.894158
	}, {
		"序号": 363,
		"模型编号": "Object1227",
		"经度": 116.04143251,
		"纬度": 30.32949055,
		"海拔高度/m": 102.366226,
		"树高度/m": 6.74254
	}, {
		"序号": 364,
		"模型编号": "Object1228",
		"经度": 116.04161959,
		"纬度": 30.32915482,
		"海拔高度/m": 102.966225,
		"树高度/m": 7.56411
	}, {
		"序号": 365,
		"模型编号": "Object1198",
		"经度": 116.06119578,
		"纬度": 30.31346351,
		"海拔高度/m": 103.002937,
		"树高度/m": 5.177676
	}, {
		"序号": 366,
		"模型编号": "Object1045",
		"经度": 116.06101384,
		"纬度": 30.313381,
		"海拔高度/m": 103.129303,
		"树高度/m": 7.457656
	}, {
		"序号": 367,
		"模型编号": "Object1200",
		"经度": 116.05937176,
		"纬度": 30.31470637,
		"海拔高度/m": 105.402946,
		"树高度/m": 15.630482
	}, {
		"序号": 368,
		"模型编号": "Object1229",
		"经度": 116.04063612,
		"纬度": 30.32985995,
		"海拔高度/m": 105.666222,
		"树高度/m": 10.69765
	}, {
		"序号": 369,
		"模型编号": "Object1075",
		"经度": 116.03737749,
		"纬度": 30.33243626,
		"海拔高度/m": 106.857765,
		"树高度/m": 11.960782
	}, {
		"序号": 370,
		"模型编号": "Object1052",
		"经度": 116.05950797,
		"纬度": 30.31431397,
		"海拔高度/m": 107.008957,
		"树高度/m": 17.69727
	}, {
		"序号": 371,
		"模型编号": "Object1201",
		"经度": 116.05975127,
		"纬度": 30.31451058,
		"海拔高度/m": 107.502945,
		"树高度/m": 12.130172
	}, {
		"序号": 372,
		"模型编号": "Object1216",
		"经度": 116.04814526,
		"纬度": 30.32354787,
		"海拔高度/m": 107.811714,
		"树高度/m": 7.917484
	}, {
		"序号": 373,
		"模型编号": "Object1051",
		"经度": 116.06011556,
		"纬度": 30.31403341,
		"海拔高度/m": 107.908958,
		"树高度/m": 11.350642
	}, {
		"序号": 374,
		"模型编号": "Object1063",
		"经度": 116.05955941,
		"纬度": 30.31484446,
		"海拔高度/m": 108.175819,
		"树高度/m": 11.590256
	}, {
		"序号": 375,
		"模型编号": "Object1207",
		"经度": 116.05892434,
		"纬度": 30.31483307,
		"海拔高度/m": 109.229347,
		"树高度/m": 10.557852
	}, {
		"序号": 376,
		"模型编号": "Object1064",
		"经度": 116.05962605,
		"纬度": 30.31511834,
		"海拔高度/m": 109.975822,
		"树高度/m": 4.771744
	}, {
		"序号": 377,
		"模型编号": "Object1048",
		"经度": 116.06111715,
		"纬度": 30.31396183,
		"海拔高度/m": 111.508957,
		"树高度/m": 6.751952
	}, {
		"序号": 378,
		"模型编号": "Object1053",
		"经度": 116.06135936,
		"纬度": 30.31421363,
		"海拔高度/m": 111.646866,
		"树高度/m": 5.394788
	}, {
		"序号": 379,
		"模型编号": "Object1049",
		"经度": 116.06126311,
		"纬度": 30.31401172,
		"海拔高度/m": 111.80896,
		"树高度/m": 12.17731
	}, {
		"序号": 380,
		"模型编号": "Object1223",
		"经度": 116.04453314,
		"纬度": 30.3270252,
		"海拔高度/m": 112.26622,
		"树高度/m": 11.104868
	}, {
		"序号": 381,
		"模型编号": "Object1046",
		"经度": 116.06090917,
		"纬度": 30.31364426,
		"海拔高度/m": 112.408958,
		"树高度/m": 3.91919
	}, {
		"序号": 382,
		"模型编号": "Object1203",
		"经度": 116.05810668,
		"纬度": 30.31619782,
		"海拔高度/m": 112.602943,
		"树高度/m": 16.786062
	}, {
		"序号": 383,
		"模型编号": "Object1065",
		"经度": 116.05987458,
		"纬度": 30.31490604,
		"海拔高度/m": 113.575821,
		"树高度/m": 10.212322
	}, {
		"序号": 384,
		"模型编号": "Object1224",
		"经度": 116.03969372,
		"纬度": 30.32987698,
		"海拔高度/m": 114.066223,
		"树高度/m": 16.383012
	}, {
		"序号": 385,
		"模型编号": "Object1202",
		"经度": 116.05734722,
		"纬度": 30.31608829,
		"海拔高度/m": 114.402946,
		"树高度/m": 19.104398
	}, {
		"序号": 386,
		"模型编号": "Object1062",
		"经度": 116.05839056,
		"纬度": 30.31528231,
		"海拔高度/m": 114.475815,
		"树高度/m": 3.498732
	}, {
		"序号": 387,
		"模型编号": "Object1080",
		"经度": 116.04825728,
		"纬度": 30.3243503,
		"海拔高度/m": 114.721436,
		"树高度/m": 10.582544
	}, {
		"序号": 388,
		"模型编号": "Object1060",
		"经度": 116.05885742,
		"纬度": 30.31612681,
		"海拔高度/m": 114.775818,
		"树高度/m": 13.409822
	}, {
		"序号": 389,
		"模型编号": "Object1057",
		"经度": 116.0592941,
		"纬度": 30.31516168,
		"海拔高度/m": 114.946869,
		"树高度/m": 3.62154
	}, {
		"序号": 390,
		"模型编号": "Object1047",
		"经度": 116.06103512,
		"纬度": 30.31376936,
		"海拔高度/m": 115.408958,
		"树高度/m": 9.414652
	}, {
		"序号": 391,
		"模型编号": "Object1225",
		"经度": 116.03963717,
		"纬度": 30.3304382,
		"海拔高度/m": 115.566223,
		"树高度/m": 12.833996
	}, {
		"序号": 392,
		"模型编号": "Object1230",
		"经度": 116.04022848,
		"纬度": 30.330052,
		"海拔高度/m": 115.866219,
		"树高度/m": 9.292422
	}, {
		"序号": 393,
		"模型编号": "Object1208",
		"经度": 116.05826481,
		"纬度": 30.3158532,
		"海拔高度/m": 116.129349,
		"树高度/m": 6.788588
	}, {
		"序号": 394,
		"模型编号": "Object1204",
		"经度": 116.05865815,
		"纬度": 30.31572062,
		"海拔高度/m": 122.502945,
		"树高度/m": 7.463318
	}, {
		"序号": 395,
		"模型编号": "Object1219",
		"经度": 116.04451618,
		"纬度": 30.32667968,
		"海拔高度/m": 122.511711,
		"树高度/m": 14.678114
	}, {
		"序号": 396,
		"模型编号": "Object1221",
		"经度": 116.04477981,
		"纬度": 30.32667909,
		"海拔高度/m": 122.766197,
		"树高度/m": 6.661158
	}, {
		"序号": 397,
		"模型编号": "Object1082",
		"经度": 116.04779381,
		"纬度": 30.32353333,
		"海拔高度/m": 123.808304,
		"树高度/m": 12.326252
	}, {
		"序号": 398,
		"模型编号": "Object1083",
		"经度": 116.04791918,
		"纬度": 30.32445273,
		"海拔高度/m": 124.108307,
		"树高度/m": 5.908424
	}, {
		"序号": 399,
		"模型编号": "Object1205",
		"经度": 116.0579618,
		"纬度": 30.31565417,
		"海拔高度/m": 125.202942,
		"树高度/m": 13.009986
	}, {
		"序号": 400,
		"模型编号": "Object1222",
		"经度": 116.04381704,
		"纬度": 30.32666081,
		"海拔高度/m": 127.566208,
		"树高度/m": 17.039082
	}, {
		"序号": 401,
		"模型编号": "Object1074",
		"经度": 116.04719833,
		"纬度": 30.32412676,
		"海拔高度/m": 127.791496,
		"树高度/m": 6.311908
	}, {
		"序号": 402,
		"模型编号": "Object1206",
		"经度": 116.05903386,
		"纬度": 30.31582817,
		"海拔高度/m": 128.202942,
		"树高度/m": 6.260706
	}, {
		"序号": 403,
		"模型编号": "Object1081",
		"经度": 116.04767154,
		"纬度": 30.32429787,
		"海拔高度/m": 128.221436,
		"树高度/m": 3.693716
	}, {
		"序号": 404,
		"模型编号": "Object1073",
		"经度": 116.04451013,
		"纬度": 30.326244,
		"海拔高度/m": 128.691498,
		"树高度/m": 6.396614
	}, {
		"序号": 405,
		"模型编号": "Object1055",
		"经度": 116.06051156,
		"纬度": 30.31469631,
		"海拔高度/m": 129.04686,
		"树高度/m": 5.797434
	}, {
		"序号": 406,
		"模型编号": "Object1232",
		"经度": 116.03756301,
		"纬度": 30.3317124,
		"海拔高度/m": 129.666183,
		"树高度/m": 8.500782
	}, {
		"序号": 407,
		"模型编号": "Object1101",
		"经度": 116.03740427,
		"纬度": 30.33164238,
		"海拔高度/m": 133.579193,
		"树高度/m": 13.024082
	}, {
		"序号": 408,
		"模型编号": "Object1218",
		"经度": 116.04494638,
		"纬度": 30.32595621,
		"海拔高度/m": 136.011719,
		"树高度/m": 10.361618
	}, {
		"序号": 409,
		"模型编号": "Object1095",
		"经度": 116.04002338,
		"纬度": 30.33067118,
		"海拔高度/m": 136.600662,
		"树高度/m": 13.934232
	}, {
		"序号": 410,
		"模型编号": "Object1220",
		"经度": 116.0450874,
		"纬度": 30.32639749,
		"海拔高度/m": 136.61171,
		"树高度/m": 8.668546
	}, {
		"序号": 411,
		"模型编号": "Object1103",
		"经度": 116.03761426,
		"纬度": 30.33134399,
		"海拔高度/m": 140.019821,
		"树高度/m": 9.57917
	}, {
		"序号": 412,
		"模型编号": "Object1098",
		"经度": 116.03878526,
		"纬度": 30.33095569,
		"海拔高度/m": 141.679184,
		"树高度/m": 13.818672
	}, {
		"序号": 413,
		"模型编号": "Object1099",
		"经度": 116.03793411,
		"纬度": 30.33212882,
		"海拔高度/m": 141.679184,
		"树高度/m": 13.45608
	}, {
		"序号": 414,
		"模型编号": "Object1100",
		"经度": 116.03856886,
		"纬度": 30.33163723,
		"海拔高度/m": 148.879196,
		"树高度/m": 11.208044
	}, {
		"序号": 415,
		"模型编号": "Object1231",
		"经度": 116.03806416,
		"纬度": 30.33161328,
		"海拔高度/m": 150.966202,
		"树高度/m": 11.838814
	}, {
		"序号": 416,
		"模型编号": "Object1089",
		"经度": 116.04511521,
		"纬度": 30.32563132,
		"海拔高度/m": 161.531372,
		"树高度/m": 18.963906
	}, {
		"序号": 417,
		"模型编号": "Object1088",
		"经度": 116.04557473,
		"纬度": 30.32579233,
		"海拔高度/m": 163.931366,
		"树高度/m": 12.923044
	}, {
		"序号": 418,
		"模型编号": "Object1090",
		"经度": 116.04562297,
		"纬度": 30.32518891,
		"海拔高度/m": 164.231369,
		"树高度/m": 3.14064
	}, {
		"序号": 419,
		"模型编号": "Object1091",
		"经度": 116.04582145,
		"纬度": 30.32547793,
		"海拔高度/m": 166.300674,
		"树高度/m": 4.094448
	}, {
		"序号": 420,
		"模型编号": "Object1086",
		"经度": 116.04609185,
		"纬度": 30.325217,
		"海拔高度/m": 169.231644,
		"树高度/m": 5.063564
	}, {
		"序号": 421,
		"模型编号": "Object1087",
		"经度": 116.04598642,
		"纬度": 30.32574924,
		"海拔高度/m": 171.33165,
		"树高度/m": 16.09994
	}]
}